{"first_piece_approval":[{"initial":"JB","shift":"1","pressNum":"401","cavityNum":"401","part":"asdfa","date":"8/11/2022","time":"11:44:51 AM","moldSet":"moldSet","purgeIn":"purgeIn","down8":"down8","processChange":"processChange"}],"setup_stabilize_complete":[{"initial":"JB","q1":"yes","q2":"yes","q3":"yes","q4":"no","q5":"yes","q6":"yes"}],"hotCheck":[{"partNum":"1234","initial":"JB","q1":"yes","zone1":"asdf","above":"asdf","zone2":"asdf","below":"asdf"}],"completeInitial1stPieceTesting":[{"initial":"JB","partNum":"asdf","q1":"Pass","q2":"Fail","q3":"Pass","q4":"Fail","q5":"Fail","tank1":"`123","q6":"Pass","tank2":"asdf","q7":"Pass"}],"reviewAndSignOff":[{"q1":"yes","qualTechSignature":"asdfa"}],"completeRemainingTesting":[{"q1":"Pass","q2":"Pass","q3":"Fail","q4":"Pass"}],"reaction1stInspectionFail":[{"initial":"JB","q1":"Yes"}]}